COPYING
README
ez_setup.py
setup.py
yaro.py
yaro.egg-info/PKG-INFO
yaro.egg-info/SOURCES.txt
yaro.egg-info/dependency_links.txt
yaro.egg-info/requires.txt
yaro.egg-info/top_level.txt
