Metadata-Version: 1.0
Name: yaro
Version: 0.6.4
Summary: A simple but non-restrictive abstraction of WSGI.
Home-page: http://lukearno.com/projects/yaro/
Author: Luke Arno
Author-email: luke.arno@gmail.com
License: LGPL
Keywords: wsgi web http request webapps
Platform: UNKNOWN
Classifier: Development Status :: 3 - Alpha
Classifier: Environment :: Web Environment
Classifier: Intended Audience :: Developers
Classifier: License :: OSI Approved :: GNU Library or Lesser General Public License (LGPL)
Classifier: Natural Language :: English
Classifier: Operating System :: OS Independent
Classifier: Programming Language :: Python
Classifier: Topic :: Software Development :: Libraries
Classifier: Topic :: Utilities
